xqrcode/__init__.py
xqrcode/errors.py
xqrcode/xqrcode.py
xqrcode-1.0.1.dist-info/LICENSE
xqrcode-1.0.1.dist-info/METADATA
xqrcode-1.0.1.dist-info/WHEEL
xqrcode-1.0.1.dist-info/top_level.txt
xqrcode-1.0.1.dist-info/RECORD
